AUTHOURS
Changelog
LICENSE
MANIFEST.in
README.md
setup.py
tickeys/CLI.py
tickeys/GUI.py
tickeys/__init__.py
tickeys/build.py
tickeys/config.py
tickeys/keyboardHandler.py
tickeys/logger.py
tickeys/requirements.txt
tickeys/run.py
tickeys/run_with_CLI.py
tickeys/soundPlayer.py
tickeys/startupHandler.py
tickeys/tickeys
tickeys/tickeys.png
tickeys/tickeys_tray.py
tickeys/tickeysui.kv
tickeys/windowManager.py
tickeys.egg-info/PKG-INFO
tickeys.egg-info/SOURCES.txt
tickeys.egg-info/dependency_links.txt
tickeys.egg-info/entry_points.txt
tickeys.egg-info/requires.txt
tickeys.egg-info/top_level.txt
tickeys/Resources/data/schemes.json
tickeys/Resources/data/Cherry_G80_3000/G80-3000.wav
tickeys/Resources/data/Cherry_G80_3000/G80-3000_fast1.wav
tickeys/Resources/data/Cherry_G80_3000/G80-3000_fast2.wav
tickeys/Resources/data/Cherry_G80_3000/G80-3000_slow1.wav
tickeys/Resources/data/Cherry_G80_3000/G80-3000_slow2.wav
tickeys/Resources/data/Cherry_G80_3494/G80-3494.wav
tickeys/Resources/data/Cherry_G80_3494/G80-3494_backspace.wav
tickeys/Resources/data/Cherry_G80_3494/G80-3494_enter.wav
tickeys/Resources/data/Cherry_G80_3494/G80-3494_fast1.wav
tickeys/Resources/data/Cherry_G80_3494/G80-3494_slow1.wav
tickeys/Resources/data/Cherry_G80_3494/G80-3494_space.wav
tickeys/Resources/data/bubble/1.wav
tickeys/Resources/data/bubble/2.wav
tickeys/Resources/data/bubble/3.wav
tickeys/Resources/data/bubble/4.wav
tickeys/Resources/data/bubble/5.wav
tickeys/Resources/data/bubble/6.wav
tickeys/Resources/data/bubble/7.wav
tickeys/Resources/data/bubble/8.wav
tickeys/Resources/data/bubble/enter.wav
tickeys/Resources/data/bubble/license.txt
tickeys/Resources/data/drum/1.wav
tickeys/Resources/data/drum/2.wav
tickeys/Resources/data/drum/3.wav
tickeys/Resources/data/drum/4.wav
tickeys/Resources/data/drum/_readme_and_license.txt
tickeys/Resources/data/drum/backspace.wav
tickeys/Resources/data/drum/enter.wav
tickeys/Resources/data/drum/space.wav
tickeys/Resources/data/mechanical/1.wav
tickeys/Resources/data/mechanical/2.wav
tickeys/Resources/data/mechanical/3.wav
tickeys/Resources/data/mechanical/4.wav
tickeys/Resources/data/mechanical/5.wav
tickeys/Resources/data/mechanical/license.txt
